{
    "version": "0",
    "id": "e1850763-1234-1234-1234-b1c2e9e5b5df",
    "detail-type": "AWS API Call via CloudTrail",
    "source": "aws.iam",
    "account": "123412341234",
    "time": "2023-07-11T20:11:18Z",
    "region": "us-east-1",
    "resources": [],
    "detail": {
        "eventVersion": "1.08",
        "userIdentity": {
            "type": "AssumedRole",
            "principalId": "AROAEXAMPLE:leo",
            "arn": "arn:aws:sts::123412341234:assumed-role/me/leo",
            "accountId": "123412341234",
            "accessKeyId": "ASIAEXAMPLE",
            "sessionContext": {
                "sessionIssuer": {
                    "type": "Role",
                    "principalId": "AROAEXAMPLE",
                    "arn": "arn:aws:iam::123412341234:role/me",
                    "accountId": "123412341234",
                    "userName": "me"
                },
                "webIdFederationData": {},
                "attributes": {
                    "creationDate": "2023-07-11T14:14:08Z",
                    "mfaAuthenticated": "false"
                }
            }
        },
        "eventTime": "2023-07-11T20:11:18Z",
        "eventSource": "iam.amazonaws.com",
        "eventName": "CreatePolicyVersion",
        "awsRegion": "us-east-1",
        "sourceIPAddress": "11.22.33.44",
        "userAgent": "AWS Internal",
        "requestParameters": {
            "setAsDefault": true,
            "policyArn": "arn:aws:iam::123412341234:policy/test-validate-policy",
            "policyDocument": "{\n    \"Version\": \"2012-10-17\",\n    \"Statement\": [\n        {\n            \"Sid\": \"VisualEditor0\",\n            \"Effect\": \"Allow\",\n            \"Action\": \"*\",\n            \"Resource\": \"*\"\n            \n            \n        }\n    ]\n}"
        },
        "responseElements": {
            "policyVersion": {
                "isDefaultVersion": true,
                "createDate": "Jul 11, 2023 8:11:18 PM",
                "versionId": "v3"
            }
        },
        "requestID": "a570e6cd-1234-1234-1234-302d64bd324b",
        "eventID": "e53be6d6-1234-1234-1234-98a464464a18",
        "readOnly": false,
        "eventType": "AwsApiCall",
        "managementEvent": true,
        "recipientAccountId": "123412341234",
        "eventCategory": "Management",
        "sessionCredentialFromConsole": "true"
    }
}